tnatlas/__init__.py
tnatlas/alignedfeature.py
tnatlas/annotate.py
tnatlas/blastn.py
tnatlas/cli.py
tnatlas/config.py
tnatlas/default.toml
tnatlas/fastx.py
tnatlas/insertion.py
tnatlas/meta.py
tnatlas/qc.py
tnatlas/utils.py
tnatlas-0.0.4.dist-info/licenses/LICENSE.txt
tnatlas-0.0.4.dist-info/METADATA
tnatlas-0.0.4.dist-info/WHEEL
tnatlas-0.0.4.dist-info/entry_points.txt
tnatlas-0.0.4.dist-info/top_level.txt
tnatlas-0.0.4.dist-info/RECORD
