Metadata-Version: 2.4
Name: tnatlas
Version: 0.0.4
Summary: Find transposon integrations in reads and align them to genomes.
Author-email: Lorea Alejaldre <lorea.alejaldre@cnb.csic.es>, Lewis Grozinger <lewis.grozinger@cnb.csic.es>, Ana Mariya Anhel <a.valdes@liverpool.ac.uk>, Angel Goni Moreno <angel.goni@cnb.csic.es>
Maintainer-email: Lewis Grozinger <lewis.grozinger@cnb.csic.es>
License-Expression: MIT
Keywords: bioinformatics,alignment,genetics,transposon,scientific
Requires-Python: >=3.8
License-File: LICENSE.txt
Requires-Dist: biopython>1.8
Requires-Dist: numpy>2.2
Requires-Dist: pandas
Requires-Dist: openpyxl
Requires-Dist: psutil
Dynamic: license-file
